{
  "routes": [
    {
      "method": "GET",
      "path": "/wtc-location-by-areas",
      "handler": "wtc-location-by-area.find",
      "config": {
        "policies": []
      }
    },
    {
      "method": "GET",
      "path": "/wtc-location-by-areas/count",
      "handler": "wtc-location-by-area.count",
      "config": {
        "policies": []
      }
    },
    {
      "method": "GET",
      "path": "/wtc-location-by-areas/:id",
      "handler": "wtc-location-by-area.findOne",
      "config": {
        "policies": []
      }
    },
    {
      "method": "POST",
      "path": "/wtc-location-by-areas",
      "handler": "wtc-location-by-area.create",
      "config": {
        "policies": []
      }
    },
    {
      "method": "PUT",
      "path": "/wtc-location-by-areas/:id",
      "handler": "wtc-location-by-area.update",
      "config": {
        "policies": []
      }
    },
    {
      "method": "DELETE",
      "path": "/wtc-location-by-areas/:id",
      "handler": "wtc-location-by-area.delete",
      "config": {
        "policies": []
      }
    }
  ]
}
